gaedevhelper/__init__.py
gaedevhelper/gae.py
gaedevhelper-0.1.0.dev0.dist-info/DESCRIPTION.rst
gaedevhelper-0.1.0.dev0.dist-info/entry_points.txt
gaedevhelper-0.1.0.dev0.dist-info/METADATA
gaedevhelper-0.1.0.dev0.dist-info/metadata.json
gaedevhelper-0.1.0.dev0.dist-info/RECORD
gaedevhelper-0.1.0.dev0.dist-info/top_level.txt
gaedevhelper-0.1.0.dev0.dist-info/WHEEL
