Metadata-Version: 2.0
Name: gaedevhelper
Version: 0.1.0.dev0
Summary: A lovely command-line helper for developing GAE applications
Home-page: https://github.com/devjoe/gae-dev-helper
Author: devjoe
Author-email: excusemejoe@gmail.com
License: MIT
Keywords: GAE,Google App Engine,dev_appserver,pygments,remote_api,gae_dev_helper
Platform: UNKNOWN
Classifier: Programming Language :: Python
Classifier: Programming Language :: Python :: 2.6
Classifier: Programming Language :: Python :: 2.7
Classifier: Programming Language :: Python :: 3
Classifier: Programming Language :: Python :: 3.1
Classifier: Programming Language :: Python :: 3.2
Classifier: Programming Language :: Python :: 3.3
Classifier: Programming Language :: Python :: 3.4
Classifier: Environment :: Console
Classifier: Intended Audience :: Developers
Classifier: Topic :: Software Development
Classifier: Topic :: System :: Networking
Classifier: Topic :: Terminals
Classifier: Topic :: Text Processing
Classifier: Topic :: Utilities
Requires-Dist: Click
Requires-Dist: Pygments
Requires-Dist: subprocess32
Requires-Dist: daemonize
